langchain_ibm/__init__.py
langchain_ibm/chat_models.py
langchain_ibm/embeddings.py
langchain_ibm/llms.py
langchain_ibm/py.typed
gigachain_ibm-0.1.8.dist-info/LICENSE
gigachain_ibm-0.1.8.dist-info/METADATA
gigachain_ibm-0.1.8.dist-info/WHEEL
gigachain_ibm-0.1.8.dist-info/RECORD
