Metadata-Version: 2.1
Name: gigachain-ibm
Version: 0.1.8
Summary: An integration package connecting IBM watsonx.ai and GigaChain
Home-page: https://github.com/ai-forever/gigachain
License: MIT
Author: IBM
Requires-Python: >=3.10,<4.0
Classifier: License :: OSI Approved :: MIT License
Classifier: Programming Language :: Python :: 3
Classifier: Programming Language :: Python :: 3.10
Classifier: Programming Language :: Python :: 3.11
Classifier: Programming Language :: Python :: 3.12
Requires-Dist: gigachain-core (>=0.2.2,<0.3)
Requires-Dist: ibm-watsonx-ai (>=1.0.8,<2.0.0)
Project-URL: Repository, https://github.com/ai-forever/gigachain
Project-URL: Source Code, https://github.com/ai-forever/gigachain/tree/master/libs/partners/ibm
